minik_vk_bot_api/__init__.py
minik_vk_bot_api/api.py
minik_vk_bot_api/config.py
minik_vk_bot_api/events.py
minik_vk_bot_api/handler.py
minik_vk_bot_api/keyboard.py
minik_vk_bot_api/longpoll.py
minik_vk_bot_api/utils.py
minik_vk_bot_api_minik-1.4.5.dist-info/LICENSE
minik_vk_bot_api_minik-1.4.5.dist-info/METADATA
minik_vk_bot_api_minik-1.4.5.dist-info/WHEEL
minik_vk_bot_api_minik-1.4.5.dist-info/top_level.txt
minik_vk_bot_api_minik-1.4.5.dist-info/RECORD
