Metadata-Version: 2.1
Name: minik-vk-bot-api-minik
Version: 1.4.5
Summary: Python VK BOT API
Home-page: https://github.com/MiniK1337/py-bot-vk-api
Author: MiniK1337
Author-email: minikkat1337@gmail.com
License: UNKNOWN
Platform: UNKNOWN
Classifier: Programming Language :: Python :: 3.7
Classifier: License :: OSI Approved :: MIT License
Classifier: Operating System :: OS Independent
